Workbook

Sheet README
B2: Marketing Campaign ROAS & Attribution Calculator
B3: A multi-touch attribution model built to stress-test Refonte's core commercial claim: a 40% boost in advertising returns.
B6: WHAT THIS IS
B7: This workbook models how marketing revenue should be credited across a customer's full path to purchase, instead of crediting 100% of the sale to the last ad someone clicked. It compares five attribution methodologies side by side (First-Touch, Last-Touch, Linear, Time-Decay, Position-Based), converts each into a Return on Ad Spend (ROAS) figure per channel, and includes a live budget-reallocation simulator for testing how close a reallocated budget can get toward a target ROAS uplift.
B9: WHY IT MATTERS
B10: Last-touch attribution (the default in most ad platforms) systematically overweights bottom-of-funnel channels like Paid Search and undervalues awareness channels like Display, Video, and Influencer. A vendor claiming a headline ROAS improvement should show that number under more than one attribution lens — this workbook lets you check that.
B12: HOW TO USE IT
B13: 1. Raw_Touchpoint_Data — 42 synthetic customer journeys (107 touchpoints) with dates, channels, and the revenue value of the resulting conversion. Every attribution model is calculated here, row by row, with visible formulas.
B14: 2. Campaign_Summary — Ad spend per channel (blue = editable input) rolled up against revenue under each attribution model, with ROAS computed live.
B15: 3. Dashboard — KPIs, a ROAS-by-channel chart, a model-comparison chart, and the Budget Reallocation Simulator. Edit the blue cells there to test different reallocation strategies against the 40% target.
B17: KEY ASSUMPTIONS (see also in-sheet notes)
B18: • Data is synthetic, generated for demonstration — not real campaign data.
... B24: Excel formulas only (SUMIFS, SUMPRODUCT, INDEX/MATCH, IF) — no macros, no external add-ins. Every number recalculates if you change the input data or spend figures.

Sheet Raw_Touchpoint_Data
A1: Customer ID | B1: Touchpoint Order | C1: Total Touchpoints in Journey | D1: Channel | E1: Touchpoint Date | F1: Journey Revenue ($) | G1: Linear Attributed ($) | H1: First-Touch Attributed ($) | I1: Last-Touch Attributed ($) | J1: Time-Decay Weight (2^order) | K1: Time-Decay Attributed ($) | L1: Position Weight | M1: Position-Based Attributed ($)
A2: CUST-001 | B2: 1 | C2: 3 | D2: Paid Search | E2: 2026-07-14 | F2: 472.42 | G2: =F2/C2 -> 157.47333 | H2: =IF(B2=1,F2,0) -> 472.42 | I2: =IF(B2=C2,F2,0) -> 0 | J2: =2^B2 -> 2 | K2: =F2*J2/SUMIFS($J$2:$J$108,$A$2:$A$108,A2) -> 67.488571 | L2: =IF(C2=1,1,IF(C2=2,0.5,IF(OR(B2=1,B2=C2),0.4,0.2/(C2-2)))) -> 0.4 | M2: =F2*L2 -> 188.968
A3: CUST-001 | B3: 2 | C3: 3 | D3: Paid Search | E3: 2026-07-15 | F3: 472.42 | G3: =F3/C3 -> 157.47333 | H3: =IF(B3=1,F3,0) -> 0 | I3: =IF(B3=C3,F3,0) -> 0 | J3: =2^B3 -> 4 | K3: =F3*J3/SUMIFS($J$2:$J$108,$A$2:$A$108,A3) -> 134.97714 | L3: =IF(C3=1,1,IF(C3=2,0.5,IF(OR(B3=1,B3=C3),0.4,0.2/(C3-2)))) -> 0.2 | M3: =F3*L3 -> 94.484
A4: CUST-001 | B4: 3 | C4: 3 | D4: Paid Search | E4: 2026-07-24 | F4: 472.42 | G4: =F4/C4 -> 157.47333 | H4: =IF(B4=1,F4,0) -> 0 | I4: =IF(B4=C4,F4,0) -> 472.42 | J4: =2^B4 -> 8 | K4: =F4*J4/SUMIFS($J$2:$J$108,$A$2:$A$108,A4) -> 269.95429 | L4: =IF(C4=1,1,IF(C4=2,0.5,IF(OR(B4=1,B4=C4),0.4,0.2/(C4-2)))) -> 0.4 | M4: =F4*L4 -> 188.968
A5: CUST-002 | B5: 1 | C5: 2 | D5: Paid Search | E5: 2026-06-02 | F5: 343 | G5: =F5/C5 -> 171.5 | H5: =IF(B5=1,F5,0) -> 343 | I5: =IF(B5=C5,F5,0) -> 0 | J5: =2^B5 -> 2 | K5: =F5*J5/SUMIFS($J$2:$J$108,$A$2:$A$108,A5) -> 114.33333 | L5: =IF(C5=1,1,IF(C5=2,0.5,IF(OR(B5=1,B5=C5),0.4,0.2/(C5-2)))) -> 0.5 | M5: =F5*L5 -> 171.5
A6: CUST-002 | B6: 2 | C6: 2 | D6: Paid Search | E6: 2026-06-04 | F6: 343 | G6: =F6/C6 -> 171.5 | H6: =IF(B6=1,F6,0) -> 0 | I6: =IF(B6=C6,F6,0) -> 343 | J6: =2^B6 -> 4 | K6: =F6*J6/SUMIFS($J$2:$J$108,$A$2:$A$108,A6) -> 228.66667 | L6: =IF(C6=1,1,IF(C6=2,0.5,IF(OR(B6=1,B6=C6),0.4,0.2/(C6-2)))) -> 0.5 | M6: =F6*L6 -> 171.5
A7: CUST-003 | B7: 1 | C7: 3 | D7: Email | E7: 2026-07-26 | F7: 215.79 | G7: =F7/C7 -> 71.93 | H7: =IF(B7=1,F7,0) -> 215.79 | I7: =IF(B7=C7,F7,0) -> 0 | J7: =2^B7 -> 2 | K7: =F7*J7/SUMIFS($J$2:$J$108,$A$2:$A$108,A7) -> 30.827143 | L7: =IF(C7=1,1,IF(C7=2,0.5,IF(OR(B7=1,B7=C7),0.4,0.2/(C7-2)))) -> 0.4 | M7: =F7*L7 -> 86.316
A8: CUST-003 | B8: 2 | C8: 3 | D8: Paid Social | E8: 2026-07-28 | F8: 215.79 | G8: =F8/C8 -> 71.93 | H8: =IF(B8=1,F8,0) -> 0 | I8: =IF(B8=C8,F8,0) -> 0 | J8: =2^B8 -> 4 | K8: =F8*J8/SUMIFS($J$2:$J$108,$A$2:$A$108,A8) -> 61.654286 | L8: =IF(C8=1,1,IF(C8=2,0.5,IF(OR(B8=1,B8=C8),0.4,0.2/(C8-2)))) -> 0.2 | M8: =F8*L8 -> 43.158
A9: CUST-003 | B9: 3 | C9: 3 | D9: Paid Social | E9: 2026-08-03 | F9: 215.79 | G9: =F9/C9 -> 71.93 | H9: =IF(B9=1,F9,0) -> 0 | I9: =IF(B9=C9,F9,0) -> 215.79 | J9: =2^B9 -> 8 | K9: =F9*J9/SUMIFS($J$2:$J$108,$A$2:$A$108,A9) -> 123.30857 | L9: =IF(C9=1,1,IF(C9=2,0.5,IF(OR(B9=1,B9=C9),0.4,0.2/(C9-2)))) -> 0.4 | M9: =F9*L9 -> 86.316
A10: CUST-004 | B10: 1 | C10: 2 | D10: Paid Search | E10: 2026-06-06 | F10: 248.49 | G10: =F10/C10 -> 124.245 | H10: =IF(B10=1,F10,0) -> 248.49 | I10: =IF(B10=C10,F10,0) -> 0 | J10: =2^B10 -> 2 | K10: =F10*J10/SUMIFS($J$2:$J$108,$A$2:$A$108,A10) -> 82.83 | L10: =IF(C10=1,1,IF(C10=2,0.5,IF(OR(B10=1,B10=C10),0.4,0.2/(C10-2)))) -> 0.5 | M10: =F10*L10 -> 124.245
A11: CUST-004 | B11: 2 | C11: 2 | D11: Influencer | E11: 2026-06-07 | F11: 248.49 | G11: =F11/C11 -> 124.245 | H11: =IF(B11=1,F11,0) -> 0 | I11: =IF(B11=C11,F11,0) -> 248.49 | J11: =2^B11 -> 4 | K11: =F11*J11/SUMIFS($J$2:$J$108,$A$2:$A$108,A11) -> 165.66 | L11: =IF(C11=1,1,IF(C11=2,0.5,IF(OR(B11=1,B11=C11),0.4,0.2/(C11-2)))) -> 0.5 | M11: =F11*L11 -> 124.245
A12: CUST-005 | B12: 1 | C12: 2 | D12: Paid Social | E12: 2026-06-30 | F12: 84.33 | G12: =F12/C12 -> 42.165 | H12: =IF(B12=1,F12,0) -> 84.33 | I12: =IF(B12=C12,F12,0) -> 0 | J12: =2^B12 -> 2 | K12: =F12*J12/SUMIFS($J$2:$J$108,$A$2:$A$108,A12) -> 28.11 | L12: =IF(C12=1,1,IF(C12=2,0.5,IF(OR(B12=1,B12=C12),0.4,0.2/(C12-2)))) -> 0.5 | M12: =F12*L12 -> 42.165
A13: CUST-005 | B13: 2 | C13: 2 | D13: Paid Search | E13: 2026-07-01 | F13: 84.33 | G13: =F13/C13 -> 42.165 | H13: =IF(B13=1,F13,0) -> 0 | I13: =IF(B13=C13,F13,0) -> 84.33 | J13: =2^B13 -> 4 | K13: =F13*J13/SUMIFS($J$2:$J$108,$A$2:$A$108,A13) -> 56.22 | L13: =IF(C13=1,1,IF(C13=2,0.5,IF(OR(B13=1,B13=C13),0.4,0.2/(C13-2)))) -> 0.5 | M13: =F13*L13 -> 42.165
... A108: CUST-042 | B108: 3 | C108: 3 | D108: Paid Search | E108: 2026-08-05 | F108: 333.58 | G108: =F108/C108 -> 111.19333 | H108: =IF(B108=1,F108,0) -> 0 | I108: =IF(B108=C108,F108,0) -> 333.58 | J108: =2^B108 -> 8 | K108: =F108*J108/SUMIFS($J$2:$J$108,$A$2:$A$108,A108) -> 190.61714 | L108: =IF(C108=1,1,IF(C108=2,0.5,IF(OR(B108=1,B108=C108),0.4,0.2/(C108-2)))) -> 0.4 | M108: =F108*L108 -> 133.432
D110: Column Totals (sanity check — should all match): | G110: =SUM(G2:G108) -> 13877.99 | H110: =SUM(H2:H108) -> 13877.99 | I110: =SUM(I2:I108) -> 13877.99 | K110: =SUM(K2:K108) -> 13877.99 | M110: =SUM(M2:M108) -> 13877.99
D111: Every model must redistribute the SAME total revenue — only the credit per channel differs. If the totals above don't match, an attribution formula is broken.

Sheet Campaign_Summary
A1: Campaign Summary — Spend vs. Attributed Revenue by Model
A2: Ad Spend is the only manual input (blue). Everything else pulls live from Raw_Touchpoint_Data.
A4: Channel | B4: Ad Spend ($) | C4: Linear Revenue | D4: First-Touch Revenue | E4: Last-Touch Revenue | F4: Time-Decay Revenue | G4: Position-Based Revenue | H4: Linear ROAS | I4: First-Touch ROAS | J4: Last-Touch ROAS | K4: Time-Decay ROAS | L4: Position-Based ROAS | M4: First-Last ROAS Gap | N4: Max Cross-Model ROAS Swing
A5: Paid Search | B5: 1600 | C5: =SUMIFS(Raw_Touchpoint_Data!$G$2:$G$108,Raw_Touchpoint_Data!$D$2:$D$108,$A5) -> 5141.4192 | D5: =SUMIFS(Raw_Touchpoint_Data!$H$2:$H$108,Raw_Touchpoint_Data!$D$2:$D$108,$A5) -> 3860.91 | E5: =SUMIFS(Raw_Touchpoint_Data!$I$2:$I$108,Raw_Touchpoint_Data!$D$2:$D$108,$A5) -> 5532.54 | F5: =SUMIFS(Raw_Touchpoint_Data!$K$2:$K$108,Raw_Touchpoint_Data!$D$2:$D$108,$A5) -> 5464.4559 | G5: =SUMIFS(Raw_Touchpoint_Data!$M$2:$M$108,Raw_Touchpoint_Data!$D$2:$D$108,$A5) -> 4880.775 | H5: =IFERROR(C5/$B5,0) -> 3.213387 | I5: =IFERROR(D5/$B5,0) -> 2.4130687 | J5: =IFERROR(E5/$B5,0) -> 3.4578375 | K5: =IFERROR(F5/$B5,0) -> 3.4152849 | L5: =IFERROR(G5/$B5,0) -> 3.0504844 | M5: =I5-J5 -> -1.0447688 | N5: =MAX(H5:L5)-MIN(H5:L5) -> 1.0447688
A6: Paid Social | B6: 900 | C6: =SUMIFS(Raw_Touchpoint_Data!$G$2:$G$108,Raw_Touchpoint_Data!$D$2:$D$108,$A6) -> 2398.5258 | D6: =SUMIFS(Raw_Touchpoint_Data!$H$2:$H$108,Raw_Touchpoint_Data!$D$2:$D$108,$A6) -> 1621.8 | E6: =SUMIFS(Raw_Touchpoint_Data!$I$2:$I$108,Raw_Touchpoint_Data!$D$2:$D$108,$A6) -> 2764.29 | F6: =SUMIFS(Raw_Touchpoint_Data!$K$2:$K$108,Raw_Touchpoint_Data!$D$2:$D$108,$A6) -> 2519.0937 | G6: =SUMIFS(Raw_Touchpoint_Data!$M$2:$M$108,Raw_Touchpoint_Data!$D$2:$D$108,$A6) -> 2242.978 | H6: =IFERROR(C6/$B6,0) -> 2.6650287 | I6: =IFERROR(D6/$B6,0) -> 1.802 | J6: =IFERROR(E6/$B6,0) -> 3.0714333 | K6: =IFERROR(F6/$B6,0) -> 2.798993 | L6: =IFERROR(G6/$B6,0) -> 2.4921978 | M6: =I6-J6 -> -1.2694333 | N6: =MAX(H6:L6)-MIN(H6:L6) -> 1.2694333
A7: Display | B7: 700 | C7: =SUMIFS(Raw_Touchpoint_Data!$G$2:$G$108,Raw_Touchpoint_Data!$D$2:$D$108,$A7) -> 1663.0442 | D7: =SUMIFS(Raw_Touchpoint_Data!$H$2:$H$108,Raw_Touchpoint_Data!$D$2:$D$108,$A7) -> 2473.33 | E7: =SUMIFS(Raw_Touchpoint_Data!$I$2:$I$108,Raw_Touchpoint_Data!$D$2:$D$108,$A7) -> 1359.49 | F7: =SUMIFS(Raw_Touchpoint_Data!$K$2:$K$108,Raw_Touchpoint_Data!$D$2:$D$108,$A7) -> 1439.6483 | G7: =SUMIFS(Raw_Touchpoint_Data!$M$2:$M$108,Raw_Touchpoint_Data!$D$2:$D$108,$A7) -> 1813.071 | H7: =IFERROR(C7/$B7,0) -> 2.3757774 | I7: =IFERROR(D7/$B7,0) -> 3.5333286 | J7: =IFERROR(E7/$B7,0) -> 1.9421286 | K7: =IFERROR(F7/$B7,0) -> 2.0566404 | L7: =IFERROR(G7/$B7,0) -> 2.5901014 | M7: =I7-J7 -> 1.5912 | N7: =MAX(H7:L7)-MIN(H7:L7) -> 1.5912
A8: Email | B8: 350 | C8: =SUMIFS(Raw_Touchpoint_Data!$G$2:$G$108,Raw_Touchpoint_Data!$D$2:$D$108,$A8) -> 1765.4233 | D8: =SUMIFS(Raw_Touchpoint_Data!$H$2:$H$108,Raw_Touchpoint_Data!$D$2:$D$108,$A8) -> 1456.77 | E8: =SUMIFS(Raw_Touchpoint_Data!$I$2:$I$108,Raw_Touchpoint_Data!$D$2:$D$108,$A8) -> 2096.05 | F8: =SUMIFS(Raw_Touchpoint_Data!$K$2:$K$108,Raw_Touchpoint_Data!$D$2:$D$108,$A8) -> 1950.0921 | G8: =SUMIFS(Raw_Touchpoint_Data!$M$2:$M$108,Raw_Touchpoint_Data!$D$2:$D$108,$A8) -> 1781.205 | H8: =IFERROR(C8/$B8,0) -> 5.0440667 | I8: =IFERROR(D8/$B8,0) -> 4.1622 | J8: =IFERROR(E8/$B8,0) -> 5.9887143 | K8: =IFERROR(F8/$B8,0) -> 5.5716917 | L8: =IFERROR(G8/$B8,0) -> 5.0891571 | M8: =I8-J8 -> -1.8265143 | N8: =MAX(H8:L8)-MIN(H8:L8) -> 1.8265143
A9: Video | B9: 750 | C9: =SUMIFS(Raw_Touchpoint_Data!$G$2:$G$108,Raw_Touchpoint_Data!$D$2:$D$108,$A9) -> 1932.0792 | D9: =SUMIFS(Raw_Touchpoint_Data!$H$2:$H$108,Raw_Touchpoint_Data!$D$2:$D$108,$A9) -> 2341.41 | E9: =SUMIFS(Raw_Touchpoint_Data!$I$2:$I$108,Raw_Touchpoint_Data!$D$2:$D$108,$A9) -> 1877.13 | F9: =SUMIFS(Raw_Touchpoint_Data!$K$2:$K$108,Raw_Touchpoint_Data!$D$2:$D$108,$A9) -> 1860.2969 | G9: =SUMIFS(Raw_Touchpoint_Data!$M$2:$M$108,Raw_Touchpoint_Data!$D$2:$D$108,$A9) -> 2074.713 | H9: =IFERROR(C9/$B9,0) -> 2.5761056 | I9: =IFERROR(D9/$B9,0) -> 3.12188 | J9: =IFERROR(E9/$B9,0) -> 2.50284 | K9: =IFERROR(F9/$B9,0) -> 2.4803958 | L9: =IFERROR(G9/$B9,0) -> 2.766284 | M9: =I9-J9 -> 0.61904 | N9: =MAX(H9:L9)-MIN(H9:L9) -> 0.64148419
A10: Influencer | B10: 600 | C10: =SUMIFS(Raw_Touchpoint_Data!$G$2:$G$108,Raw_Touchpoint_Data!$D$2:$D$108,$A10) -> 977.49833 | D10: =SUMIFS(Raw_Touchpoint_Data!$H$2:$H$108,Raw_Touchpoint_Data!$D$2:$D$108,$A10) -> 2123.77 | E10: =SUMIFS(Raw_Touchpoint_Data!$I$2:$I$108,Raw_Touchpoint_Data!$D$2:$D$108,$A10) -> 248.49 | F10: =SUMIFS(Raw_Touchpoint_Data!$K$2:$K$108,Raw_Touchpoint_Data!$D$2:$D$108,$A10) -> 644.40314 | G10: =SUMIFS(Raw_Touchpoint_Data!$M$2:$M$108,Raw_Touchpoint_Data!$D$2:$D$108,$A10) -> 1085.248 | H10: =IFERROR(C10/$B10,0) -> 1.6291639 | I10: =IFERROR(D10/$B10,0) -> 3.5396167 | J10: =IFERROR(E10/$B10,0) -> 0.41415 | K10: =IFERROR(F10/$B10,0) -> 1.0740052 | L10: =IFERROR(G10/$B10,0) -> 1.8087467 | M10: =I10-J10 -> 3.1254667 | N10: =MAX(H10:L10)-MIN(H10:L10) -> 3.1254667
A11: TOTAL / BLENDED | B11: =SUM(B5:B10) -> 4900 | C11: =SUM(C5:C10) -> 13877.99 | D11: =SUM(D5:D10) -> 13877.99 | E11: =SUM(E5:E10) -> 13877.99 | F11: =SUM(F5:F10) -> 13877.99 | G11: =SUM(G5:G10) -> 13877.99 | H11: =IFERROR(C11/$B11,0) -> 2.8322429 | I11: =IFERROR(D11/$B11,0) -> 2.8322429 | J11: =IFERROR(E11/$B11,0) -> 2.8322429 | K11: =IFERROR(F11/$B11,0) -> 2.8322429 | L11: =IFERROR(G11/$B11,0) -> 2.8322429
A13: Note: ROAS shown as a multiple (e.g. 3.20x = $3.20 revenue per $1.00 spent). Compare the Last-Touch column (what most ad platforms report natively) against Linear/Time-Decay/Position-Based to see how much credit is being over- or under-stated for upper-funnel channels.

Sheet Dashboard
A1: Marketing ROAS Dashboard
A2: All figures pull live from Campaign_Summary. Blue cells in the simulator are editable.
A4: Total Ad Spend | B4: Total Revenue (Linear model) | C4: Blended ROAS (Linear) | D4: Max Cross-Model ROAS Swing
A5: =Campaign_Summary!B11 -> 4900 | B5: =Campaign_Summary!C11 -> 13877.99 | C5: =Campaign_Summary!H11 -> 2.8322429 | D5: =MAX(Campaign_Summary!N5:N10) -> 3.1254667
A7: Best channel by Linear ROAS: | C7: =INDEX(Campaign_Summary!A5:A10,MATCH(MAX(Campaign_Summary!H5:H10),Campaign_Summary!H5:H10,0)) -> Email
A8: Most undervalued by last-touch (biggest first-touch minus last-touch ROAS gap): | C8: =INDEX(Campaign_Summary!A5:A10,MATCH(MAX(Campaign_Summary!M5:M10),Campaign_Summary!M5:M10,0)) -> Influencer
A48: Budget Reallocation Simulator
A49: Edit the blue % Reallocation cells to shift budget toward higher-ROAS channels. Projected Revenue assumes each channel's current Linear ROAS holds at the margin — a simplifying assumption; real budgets face diminishing returns as spend increases.
A51: Channel | B51: Current Spend | C51: Current ROAS | D51: % Reallocation | E51: New Spend | F51: New Proj. Revenue
A52: =Campaign_Summary!A5 -> Paid Search | B52: =Campaign_Summary!B5 -> 1600 | C52: =Campaign_Summary!H5 -> 3.213387 | D52: 0.15 | E52: =B52*(1+D52) -> 1840 | F52: =E52*C52 -> 5912.632
A53: =Campaign_Summary!A6 -> Paid Social | B53: =Campaign_Summary!B6 -> 900 | C53: =Campaign_Summary!H6 -> 2.6650287 | D53: 0.05 | E53: =B53*(1+D53) -> 945 | F53: =E53*C53 -> 2518.4521
A54: =Campaign_Summary!A7 -> Display | B54: =Campaign_Summary!B7 -> 700 | C54: =Campaign_Summary!H7 -> 2.3757774 | D54: -0.2 | E54: =B54*(1+D54) -> 560 | F54: =E54*C54 -> 1330.4353
A55: =Campaign_Summary!A8 -> Email | B55: =Campaign_Summary!B8 -> 350 | C55: =Campaign_Summary!H8 -> 5.0440667 | D55: 0.3 | E55: =B55*(1+D55) -> 455 | F55: =E55*C55 -> 2295.0503
A56: =Campaign_Summary!A9 -> Video | B56: =Campaign_Summary!B9 -> 750 | C56: =Campaign_Summary!H9 -> 2.5761056 | D56: -0.1 | E56: =B56*(1+D56) -> 675 | F56: =E56*C56 -> 1738.8712
A57: =Campaign_Summary!A10 -> Influencer | B57: =Campaign_Summary!B10 -> 600 | C57: =Campaign_Summary!H10 -> 1.6291639 | D57: -0.35 | E57: =B57*(1+D57) -> 390 | F57: =E57*C57 -> 635.37392
A58: TOTAL | B58: =SUM(B52:B57) -> 4900 | E58: =SUM(E52:E57) -> 4865 | F58: =SUM(F52:F57) -> 14430.815
A60: Baseline Blended ROAS: | C60: =Campaign_Summary!H11 -> 2.8322429
A61: Target Uplift: | C61: 0.4
A62: Target ROAS: | C62: =C60*(1+C61) -> 3.96514
A63: Projected New ROAS: | C63: =IFERROR(F58/B58,0) -> 2.9450643
A64: Actual Uplift Achieved: | C64: =C63/C60-1 -> 0.039834659
A65: Gap to Target: | C65: =C64-C61 -> -0.36016534
